setup.py
salure_helpers/salesforce/__init__.py
salure_helpers/salesforce/salesforce.py
salure_helpers_salesforce.egg-info/PKG-INFO
salure_helpers_salesforce.egg-info/SOURCES.txt
salure_helpers_salesforce.egg-info/dependency_links.txt
salure_helpers_salesforce.egg-info/not-zip-safe
salure_helpers_salesforce.egg-info/requires.txt
salure_helpers_salesforce.egg-info/top_level.txt